{
  "seed": 1234,
  "steps": {
    "env": {
      "python": "3.8.10",
      "lib_versions": {
        "numpy": "1.23.5",
        "pandas": "2.0.3",
        "scikit-learn": "1.3.2",
        "tensorflow": "2.12.0",
        "keras": "2.12.0",
        "matplotlib": "3.7.5",
        "seaborn": "0.13.2"
      }
    },
    "data_list": {
      "train": {
        "classes": {
          "cats": 1000,
          "dogs": 1000
        }
      },
      "test": {
        "classes": {
          "cats": 500,
          "dogs": 500
        }
      },
      "full": {}
    },
    "preprocessing": {
      "preprocess_fn": "preprocess_fp",
      "target_size": [
        150,
        150
      ]
    },
    "model_info": {
      "model_path": "catsdogs_model.h5",
      "input_shape": [
        150,
        150
      ],
      "param_count": 2260546
    },
    "summary_notes": {
      "best_metric": "Accuracy: 0.949 (95% CI: 0.935-0.962)",
      "baseline_acc": 0.548,
      "observed_improvement": 0.4009999999999999,
      "p_value": 0.0,
      "effect_size": 1.0190546442795032,
      "interpretation": "✅ Statistically significant improvement over baseline."
    },
    "split": {
      "mode": "external_train_test",
      "n_train": 2000,
      "n_test": 1000,
      "seed": 1234
    },
    "metrics": {
      "accuracy": 0.949,
      "accuracy_ci": {
        "lower": 0.935,
        "upper": 0.9620249999999999
      },
      "precision": {
        "cats": 0.9535353535353536,
        "dogs": 0.9445544554455445
      },
      "recall": {
        "cats": 0.944,
        "dogs": 0.954
      },
      "f1": {
        "cats": 0.9487437185929648,
        "dogs": 0.9492537313432836
      },
      "support": {
        "cats": 500,
        "dogs": 500
      },
      "macro": {
        "precision": 0.949044904490449,
        "recall": 0.949,
        "f1": 0.9489987249681242
      },
      "micro": {
        "precision": 0.949,
        "recall": 0.949,
        "f1": 0.949
      }
    },
    "baseline": {
      "accuracy": 0.548,
      "precision": [
        0.541958041958042,
        0.5560747663551402
      ],
      "recall": [
        0.62,
        0.476
      ],
      "f1": [
        0.5783582089552238,
        0.5129310344827587
      ],
      "y_pred": [
        0,
        0,
        0,
        0,
        0,
        0,
        0,
        1,
        0,
        0,
        0,
        1,
        0,
        1,
        1,
        0,
        0,
        0,
        0,
        1,
        1,
        1,
        0,
        0,
        0,
        1,
        0,
        0,
        0,
        1,
        0,
        1,
        0,
        0,
        0,
        0,
        0,
        0,
        0,
        0,
        0,
        1,
        0,
        0,
        1,
        0,
        1,
        0,
        0,
        0,
        1,
        1,
        0,
        1,
        0,
        1,
        0,
        0,
        1,
        0,
        0,
        0,
        1,
        1,
        1,
        0,
        0,
        0,
        1,
        1,
        1,
        1,
        0,
        0,
        1,
        1,
        0,
        1,
        1,
        0,
        0,
        0,
        0,
        0,
        0,
        0,
        1,
        1,
        1,
        1,
        1,
        0,
        0,
        1,
        1,
        0,
        0,
        0,
        0,
        0,
        0,
        0,
        0,
        1,
        0,
        1,
        0,
        0,
        0,
        0,
        0,
        1,
        1,
        1,
        0,
        1,
        1,
        1,
        0,
        1,
        1,
        0,
        0,
        1,
        0,
        1,
        0,
        1,
        0,
        0,
        0,
        1,
        0,
        0,
        1,
        0,
        0,
        0,
        0,
        0,
        1,
        1,
        0,
        1,
        0,
        0,
        0,
        0,
        1,
        0,
        0,
        0,
        1,
        0,
        0,
        1,
        1,
        1,
        1,
        0,
        0,
        1,
        0,
        1,
        1,
        1,
        1,
        0,
        1,
        0,
        0,
        0,
        1,
        0,
        1,
        0,
        1,
        0,
        0,
        0,
        0,
        1,
        1,
        1,
        0,
        0,
        1,
        1,
        0,
        0,
        0,
        0,
        0,
        0,
        1,
        0,
        1,
        0,
        0,
        1,
        1,
        1,
        1,
        0,
        0,
        1,
        1,
        0,
        0,
        1,
        0,
        1,
        0,
        1,
        0,
        0,
        1,
        0,
        0,
        0,
        0,
        0,
        0,
        0,
        0,
        0,
        0,
        0,
        0,
        0,
        0,
        0,
        0,
        0,
        1,
        1,
        0,
        0,
        1,
        1,
        1,
        1,
        0,
        1,
        0,
        1,
        1,
        0,
        0,
        0,
        0,
        1,
        0,
        0,
        0,
        1,
        1,
        1,
        1,
        0,
        1,
        0,
        1,
        0,
        0,
        1,
        0,
        0,
        0,
        1,
        1,
        1,
        1,
        0,
        0,
        1,
        0,
        1,
        0,
        0,
        0,
        0,
        0,
        1,
        0,
        0,
        0,
        1,
        1,
        0,
        0,
        0,
        0,
        0,
        1,
        1,
        0,
        0,
        1,
        0,
        0,
        1,
        0,
        1,
        1,
        0,
        0,
        0,
        0,
        0,
        0,
        0,
        0,
        0,
        0,
        0,
        0,
        1,
        1,
        0,
        1,
        0,
        0,
        0,
        0,
        0,
        0,
        1,
        1,
        0,
        0,
        0,
        0,
        0,
        0,
        0,
        0,
        1,
        0,
        1,
        0,
        1,
        1,
        1,
        1,
        0,
        1,
        0,
        0,
        0,
        1,
        0,
        1,
        0,
        0,
        0,
        0,
        1,
        1,
        0,
        1,
        0,
        0,
        1,
        0,
        0,
        0,
        1,
        1,
        1,
        1,
        1,
        0,
        1,
        1,
        0,
        1,
        1,
        0,
        0,
        1,
        0,
        0,
        0,
        0,
        0,
        1,
        0,
        1,
        1,
        1,
        0,
        0,
        0,
        0,
        0,
        1,
        1,
        0,
        0,
        0,
        0,
        1,
        0,
        0,
        0,
        0,
        1,
        1,
        0,
        1,
        1,
        0,
        0,
        1,
        1,
        1,
        1,
        0,
        0,
        0,
        1,
        1,
        1,
        0,
        1,
        1,
        1,
        0,
        0,
        0,
        1,
        0,
        1,
        0,
        0,
        1,
        0,
        0,
        1,
        1,
        1,
        0,
        1,
        1,
        1,
        0,
        1,
        0,
        0,
        0,
        0,
        1,
        0,
        0,
        0,
        0,
        1,
        0,
        0,
        0,
        1,
        0,
        1,
        1,
        0,
        0,
        1,
        1,
        0,
        0,
        0,
        0,
        0,
        0,
        0,
        1,
        0,
        0,
        0,
        0,
        1,
        0,
        0,
        0,
        0,
        0,
        1,
        0,
        0,
        0,
        0,
        0,
        1,
        0,
        1,
        1,
        0,
        0,
        0,
        1,
        0,
        0,
        0,
        1,
        1,
        0,
        0,
        0,
        1,
        0,
        0,
        1,
        0,
        1,
        0,
        0,
        0,
        1,
        1,
        0,
        1,
        0,
        0,
        0,
        1,
        1,
        1,
        0,
        0,
        1,
        0,
        1,
        1,
        1,
        0,
        0,
        0,
        1,
        0,
        1,
        0,
        0,
        0,
        1,
        1,
        0,
        0,
        0,
        1,
        1,
        0,
        0,
        1,
        0,
        1,
        1,
        0,
        0,
        0,
        1,
        0,
        1,
        1,
        1,
        0,
        0,
        0,
        0,
        0,
        0,
        0,
        0,
        1,
        1,
        1,
        0,
        0,
        1,
        1,
        1,
        1,
        0,
        1,
        0,
        0,
        0,
        0,
        0,
        0,
        1,
        0,
        0,
        1,
        1,
        1,
        1,
        1,
        1,
        0,
        1,
        0,
        0,
        0,
        1,
        0,
        0,
        0,
        0,
        1,
        1,
        1,
        1,
        0,
        1,
        0,
        0,
        1,
        0,
        0,
        1,
        1,
        0,
        0,
        1,
        1,
        1,
        1,
        1,
        0,
        1,
        0,
        1,
        0,
        1,
        0,
        1,
        0,
        1,
        1,
        0,
        0,
        1,
        1,
        1,
        1,
        0,
        0,
        1,
        1,
        1,
        1,
        1,
        1,
        0,
        1,
        0,
        0,
        1,
        1,
        0,
        1,
        1,
        1,
        1,
        0,
        0,
        1,
        0,
        1,
        0,
        0,
        0,
        0,
        0,
        1,
        1,
        0,
        1,
        0,
        1,
        1,
        1,
        0,
        0,
        1,
        1,
        0,
        1,
        0,
        1,
        0,
        0,
        1,
        0,
        0,
        0,
        1,
        1,
        1,
        1,
        1,
        0,
        0,
        0,
        1,
        1,
        0,
        1,
        1,
        0,
        0,
        1,
        1,
        0,
        0,
        0,
        0,
        0,
        1,
        1,
        1,
        1,
        1,
        0,
        0,
        1,
        0,
        0,
        0,
        1,
        1,
        0,
        1,
        1,
        0,
        0,
        1,
        1,
        1,
        1,
        0,
        1,
        0,
        0,
        1,
        1,
        1,
        0,
        1,
        0,
        1,
        0,
        1,
        1,
        0,
        1,
        1,
        1,
        0,
        1,
        0,
        1,
        0,
        0,
        1,
        1,
        1,
        0,
        0,
        0,
        0,
        0,
        1,
        1,
        0,
        1,
        1,
        1,
        0,
        1,
        1,
        0,
        1,
        0,
        1,
        0,
        0,
        1,
        0,
        1,
        1,
        0,
        0,
        0,
        0,
        0,
        0,
        1,
        0,
        0,
        1,
        1,
        1,
        0,
        0,
        0,
        0,
        0,
        0,
        0,
        0,
        0,
        0,
        0,
        0,
        0,
        0,
        1,
        1,
        0,
        0,
        0,
        0,
        0,
        1,
        0,
        1,
        1,
        1,
        1,
        0,
        0,
        1,
        1,
        0,
        0,
        0,
        1,
        0,
        0,
        0,
        0,
        1,
        1,
        0,
        1,
        1,
        1,
        0,
        0,
        0,
        0,
        1,
        0,
        1,
        1,
        1,
        1,
        1,
        0,
        0,
        0,
        0,
        0,
        1,
        0,
        1,
        1,
        0,
        0,
        1,
        1,
        1,
        0,
        0,
        0,
        1,
        1,
        1,
        0,
        0,
        1,
        0,
        0,
        0,
        0,
        0,
        0,
        1,
        1,
        0,
        1,
        0,
        1,
        0,
        0,
        0,
        0,
        0,
        1,
        1,
        1,
        1,
        0,
        0,
        0,
        0,
        0,
        0,
        1,
        1,
        0,
        0,
        0,
        1,
        1,
        0,
        1,
        1,
        0,
        0,
        1,
        0,
        0,
        1,
        0,
        0,
        1,
        1,
        1,
        1,
        0,
        1,
        1,
        0,
        1,
        0,
        0,
        1,
        0,
        1,
        0,
        0,
        1,
        1,
        1,
        0,
        1,
        1,
        0,
        0,
        0,
        0,
        0,
        0,
        0,
        0,
        1,
        0,
        1,
        1,
        1,
        1,
        0,
        1,
        0,
        0,
        0,
        1,
        1,
        1,
        1,
        0,
        1,
        1,
        1,
        0,
        1,
        0,
        0,
        1,
        1,
        1,
        1,
        0,
        0,
        1,
        1,
        0,
        0,
        1,
        0,
        1,
        1,
        0,
        0,
        1,
        0,
        1
      ]
    },
    "stats_test": {
      "observed_diff": 0.4009999999999999,
      "p_value": 0.0,
      "effect_size": 1.0190546442795032
    },
    "confusion_matrix": null,
    "roc": {
      "per_class": {
        "dogs": 0.990416
      },
      "macro": 0.990416
    },
    "pr": {
      "per_class": {
        "dogs": 0.990887613363042
      },
      "macro": 0.990887613363042
    },
    "calibration": {
      "brier": 0.07742144912481308,
      "ece": 0.0200243022441864,
      "mean_confidence": 0.9683321714401245,
      "mean_entropy": 0.08315977454185486
    },
    "robustness": {
      "clean_acc_sample": 0.96,
      "gaussian_noise_acc": 0.895,
      "blur_acc": 0.905,
      "jpeg_acc": 0.905,
      "occlusion_acc": 0.935
    },
    "explainability": {
      "gradcam": [],
      "integrated_gradients": [],
      "overlap": {},
      "stability": null
    },
    "efficiency": {
      "params": 2260546,
      "model_size_mb": 8.94,
      "latency_s_per_image": 0.015191126585006714,
      "peak_memory_mb": 1458.53,
      "quantization_note": "Quantization and pruning were not applied in this evaluation."
    },
    "plots": {}
  }
}